hf_mtask_trainer/__init__.py
hf_mtask_trainer/mixins.py
hf_mtask_trainer/state.py
hf_mtask_trainer/trainer.py
hf_mtask_trainer/types.py
hf_mtask_trainer-0.0.5.dist-info/LICENSE
hf_mtask_trainer-0.0.5.dist-info/METADATA
hf_mtask_trainer-0.0.5.dist-info/WHEEL
hf_mtask_trainer-0.0.5.dist-info/top_level.txt
hf_mtask_trainer-0.0.5.dist-info/RECORD
