Metadata-Version: 2.2
Name: hf-mtask-trainer
Version: 0.0.5
Summary: A HF Trainer Implementation for Multitask Training Logs
Author: zipzou
License: MIT License
Project-URL: Homepage, https://github.com/zipzou/hf-multitask-trainer
Classifier: Programming Language :: Python :: 3
Classifier: Programming Language :: Python :: 3.7
Classifier: Programming Language :: Python :: 3.8
Classifier: Programming Language :: Python :: 3.9
Classifier: Programming Language :: Python :: 3.10
Classifier: Programming Language :: Python :: 3.11
Requires-Python: >=3.7
License-File: LICENSE
Requires-Dist: torch
Requires-Dist: transformers>=4.47.0
Requires-Dist: accelerate
Provides-Extra: test
Requires-Dist: pytest; extra == "test"
